statistical_simulation_tools/__init__.py
statistical_simulation_tools/distribution_fitter.py
statistical_simulation_tools/distribution_validator.py
statistical_simulation_tools/utils.py
statistical_simulation_tools-0.2.1.dist-info/LICENSE
statistical_simulation_tools-0.2.1.dist-info/METADATA
statistical_simulation_tools-0.2.1.dist-info/WHEEL
statistical_simulation_tools-0.2.1.dist-info/top_level.txt
statistical_simulation_tools-0.2.1.dist-info/RECORD
