Metadata-Version: 2.1
Name: statistical-simulation-tools
Version: 0.2.1
Summary: Tools for fitting, and validating distributions
Requires-Python: >=3.7,<=3.11
License-File: LICENSE
Requires-Dist: black >22.10.0
Requires-Dist: distlib ~=0.3.7
Requires-Dist: flake8 >=5.0.4
Requires-Dist: isort >=5.10.0
Requires-Dist: matplotlib >=3.5.0
Requires-Dist: numpy >=1.21.6
Requires-Dist: pandas >=1.3.5
Requires-Dist: pre-commit >=2.21.0
Requires-Dist: python-dateutil ~=2.8.2
Requires-Dist: PyYAML ~=6.0.1
Requires-Dist: scipy >=1.7.0
Requires-Dist: seaborn >=0.12.2
